{
    "name": "时序异常检测",
    "id": "time_series_anomaly_detection",
    "description": "时序异常检测专注于识别时序数据中不符合预期模式、趋势或周期性规律的异常点或异常时段。这些异常可能由系统故障、外部冲击、数据录入错误或罕见事件等多种因素引起，对于及时响应、风险评估及业务决策具有重大意义。",
    "is_trainable": true,
    "pretrained": [
        {
            "name": "DLinear_ad",
            "description": "DLinear_ad结构简单，效率高且易用的时序异常检测模型",
            "inference_model_url": "https://paddle-model-ecology.bj.bcebos.com/paddlex/official_inference_model/paddle3.0.0/DLinear_ad_infer.tar",
            "pretrained_model_url": "https://paddle-model-ecology.bj.bcebos.com/paddlex/official_pretrained_model/DLinear_ad_pretrained.pdparams",
            "model_size": "72.8 K"
        },
        {
            "name": "Nonstationary_ad",
            "description": "基于transformer结构，针对性优化非平稳时间序列的异常检测模型",
            "inference_model_url": "https://paddle-model-ecology.bj.bcebos.com/paddlex/official_inference_model/paddle3.0.0/Nonstationary_ad_infer.tar",
            "pretrained_model_url": "https://paddle-model-ecology.bj.bcebos.com/paddlex/official_pretrained_model/Nonstationary_ad_pretrained.pdparams",
            "model_size": "1.5 M"
        },
        {
            "name": "AutoEncoder_ad",
            "description": "AutoEncoder_ad是经典的自编码结构的效率高且易用的时序异常检测模型",
            "inference_model_url": "https://paddle-model-ecology.bj.bcebos.com/paddlex/official_inference_model/paddle3.0.0/AutoEncoder_ad_infer.tar",
            "pretrained_model_url": "https://paddle-model-ecology.bj.bcebos.com/paddlex/official_pretrained_model/AutoEncoder_ad_pretrained.pdparams",
            "model_size": "32 K"
        },
        {
            "name": "PatchTST_ad",
            "description": "PatchTST是兼顾局部模式和全局依赖关系的高精度时序异常检测模型",
            "inference_model_url": "https://paddle-model-ecology.bj.bcebos.com/paddlex/official_inference_model/paddle3.0.0/PatchTST_ad_infer.tar",
            "pretrained_model_url": "https://paddle-model-ecology.bj.bcebos.com/paddlex/official_pretrained_model/PatchTST_ad_pretrained.pdparams",
            "model_size": "164 K"
        }
    ]
}